LICENSE
MANIFEST.in
README.md
setup.py
tap_darksky/__init__.py
tap_darksky/client.py
tap_darksky/discover.py
tap_darksky/schema.py
tap_darksky/streams.py
tap_darksky/sync.py
tap_darksky/transform.py
tap_darksky.egg-info/PKG-INFO
tap_darksky.egg-info/SOURCES.txt
tap_darksky.egg-info/dependency_links.txt
tap_darksky.egg-info/entry_points.txt
tap_darksky.egg-info/requires.txt
tap_darksky.egg-info/top_level.txt
tap_darksky/schemas/forecast.json