Metadata-Version: 1.1
Name: tap-darksky
Version: 0.0.2
Summary: Singer.io tap for extracting data from the Darksky API
Home-page: UNKNOWN
Author: jeff.huth@bytecode.io
Author-email: UNKNOWN
License: UNKNOWN
Platform: UNKNOWN
Classifier: Programming Language :: Python :: 3 :: Only
